cyint_regressions/__init__.py
cyint_regressions-1.0.0.dist-info/LICENSE
cyint_regressions-1.0.0.dist-info/METADATA
cyint_regressions-1.0.0.dist-info/WHEEL
cyint_regressions-1.0.0.dist-info/top_level.txt
cyint_regressions-1.0.0.dist-info/RECORD
