Metadata-Version: 2.1
Name: cyint-regressions
Version: 1.0.0
Summary: Helper module to automatically create the best regressions for your data
Home-page: https://github.com/CYINT/regressions
Author: Daniel Fredriksen
Author-email: dfredriksen@cyint.technology
License: MIT
Platform: UNKNOWN
